{"installedGatsbyVersion":"4.2.0","gatsbyCliVersion":"4.2.0","dependencies":["@emotion/react@^11.7.0","@emotion/styled@^11.6.0","autoprefixer@^10.4.0","gatsby@^4.2.0","gatsby-plugin-emotion@^7.2.0","gatsby-plugin-image@^2.2.0","gatsby-plugin-manifest@^4.2.0","gatsby-plugin-react-helmet@^5.2.0","gatsby-plugin-sass@^5.2.0","gatsby-plugin-sharp@^4.2.0","gatsby-plugin-sitemap@^5.2.0","gatsby-source-contentful@^7.0.0","gatsby-source-filesystem@^4.2.0","gatsby-transformer-sharp@^4.2.0","react@^17.0.1","react-dom@^17.0.1","react-helmet@^6.1.0","sass@^1.43.4","tailwindcss@^2.2.19","twin.macro@^2.8.1"],"devDependencies":["typescript@^4.5.2","typescript-language-server@^0.8.1","vscode-langservers-extracted@^3.0.2"],"eventType":"CLI_COMMAND_METADATA","sessionId":"44489bf4-ecc6-44b2-9378-171a84645141","time":"2021-11-29T20:24:07.268Z","machineId":"2995e54f-444d-460e-ac81-f7647b68879b","componentId":"gatsby-cli","osInformation":{"nodeVersion":"v16.13.0","platform":"linux","release":"5.10.60.1-microsoft-standard-WSL2","cpus":"Intel(R) Core(TM) i7-9750H CPU @ 2.60GHz","arch":"x64","ci":false,"ciName":null,"docker":false,"termProgram":"WindowsTerminal","isTTY":true},"componentVersion":"3.2.0","dbEngine":"redux","features":[],"repositoryId":"git:c368a3f4c1869deb8abeb2bf471da744989c4347437ae73c468c352dea2f89f3","repositoryData":{"provider":"3aeb002460381c6f258e8395d3026f571f0d9a76488dcd837639b13aed316560","owner":"86b166793fabb20ff7b53e5b5325d32b7a05554df493ca144679a222307d3c96","name":"2545525911919594083d42e0ab0d7deca4be4a276ecb48feac3a4d8f57f7b349"}}
{"installedGatsbyVersion":"4.2.0","gatsbyCliVersion":"4.2.0","siteHash":"9a4f6262dd15719a672b5fa5cfda4664","eventType":"CLI_RAW_COMMAND_DEVELOP","sessionId":"44489bf4-ecc6-44b2-9378-171a84645141","time":"2021-11-29T20:24:07.957Z","machineId":"2995e54f-444d-460e-ac81-f7647b68879b","componentId":"gatsby-cli","osInformation":{"nodeVersion":"v16.13.0","platform":"linux","release":"5.10.60.1-microsoft-standard-WSL2","cpus":"Intel(R) Core(TM) i7-9750H CPU @ 2.60GHz","arch":"x64","ci":false,"ciName":null,"docker":false,"termProgram":"WindowsTerminal","isTTY":true},"componentVersion":"3.2.0","dbEngine":"redux","features":[],"repositoryId":"git:c368a3f4c1869deb8abeb2bf471da744989c4347437ae73c468c352dea2f89f3","repositoryData":{"provider":"3aeb002460381c6f258e8395d3026f571f0d9a76488dcd837639b13aed316560","owner":"86b166793fabb20ff7b53e5b5325d32b7a05554df493ca144679a222307d3c96","name":"2545525911919594083d42e0ab0d7deca4be4a276ecb48feac3a4d8f57f7b349"}}
{"installedGatsbyVersion":"4.2.0","gatsbyCliVersion":"-0.0.0","dependencies":["@emotion/react@^11.7.0","@emotion/styled@^11.6.0","autoprefixer@^10.4.0","gatsby@^4.2.0","gatsby-plugin-emotion@^7.2.0","gatsby-plugin-image@^2.2.0","gatsby-plugin-manifest@^4.2.0","gatsby-plugin-react-helmet@^5.2.0","gatsby-plugin-sass@^5.2.0","gatsby-plugin-sharp@^4.2.0","gatsby-plugin-sitemap@^5.2.0","gatsby-source-contentful@^7.0.0","gatsby-source-filesystem@^4.2.0","gatsby-transformer-sharp@^4.2.0","react@^17.0.1","react-dom@^17.0.1","react-helmet@^6.1.0","sass@^1.43.4","tailwindcss@^2.2.19","twin.macro@^2.8.1"],"devDependencies":["typescript@^4.5.2","typescript-language-server@^0.8.1","vscode-langservers-extracted@^3.0.2"],"eventType":"CLI_COMMAND_METADATA","sessionId":"44489bf4-ecc6-44b2-9378-171a84645141","time":"2021-11-29T20:24:20.185Z","machineId":"2995e54f-444d-460e-ac81-f7647b68879b","componentId":"gatsby-cli","osInformation":{"nodeVersion":"v16.13.0","platform":"linux","release":"5.10.60.1-microsoft-standard-WSL2","cpus":"Intel(R) Core(TM) i7-9750H CPU @ 2.60GHz","arch":"x64","ci":false,"ciName":null,"docker":false,"termProgram":"WindowsTerminal","isTTY":true},"componentVersion":"3.2.0","dbEngine":"redux","features":[],"repositoryId":"git:c368a3f4c1869deb8abeb2bf471da744989c4347437ae73c468c352dea2f89f3","repositoryData":{"provider":"3aeb002460381c6f258e8395d3026f571f0d9a76488dcd837639b13aed316560","owner":"86b166793fabb20ff7b53e5b5325d32b7a05554df493ca144679a222307d3c96","name":"2545525911919594083d42e0ab0d7deca4be4a276ecb48feac3a4d8f57f7b349"}}
